cli.py
modsys/__init__.py
modsys/client.py
modsys/const.py
modsys/exceptions.py
modsys/manager.py
modsys/resource.py
modsys/connectors/__init__.py
modsys/connectors/aws/__init__.py
modsys/connectors/google/__init__.py
modsys/connectors/google/base.py
modsys/connectors/google/cloud.py
modsys/connectors/google/local.py
modsys/connectors/microsoft/__init__.py
modsys/connectors/openai/__init__.py
modsys/connectors/openai/base.py
modsys/connectors/openai/cloud.py
modsys/connectors/openai/local.py
modsys/connectors/sightengine/__init__.py
modsys/connectors/sightengine/base.py
modsys/connectors/sightengine/cloud.py
modsys/connectors/sightengine/local.py
modsys/connectors/spot/__init__.py
modsys/database/__init__.py
modsys/database/firebase/__init__.py
modsys/database/firebase/base.py
modsys/database/firebase/cloud.py
modsys/database/firebase/local.py
modsys/database/mongo/__init__.py
modsys/database/mysql/__init__.py
modsys/database/postgres/__init__.py
modsys/database/supabase/__init__.py
modsys/database/supabase/base.py
modsys/database/supabase/cloud.py
modsys/database/supabase/local.py
modsys/plugins/__init__.py
modsys/plugins/evaluations.py
modsys/plugins/grading.py
modsys/plugins/prompts.py
modsys/plugins/utils.py
modsys/plugins/validation.py
modsys/service/__init__.py
modsys/service/graphql/__init__.py
modsys/service/json/__init__.py
modsys/service/json/base.py
modsys/service/json/cloud.py
modsys/service/json/local.py
modsys/tests/__init__.py
modsys-0.5.1.dist-info/LICENSE
modsys-0.5.1.dist-info/METADATA
modsys-0.5.1.dist-info/WHEEL
modsys-0.5.1.dist-info/entry_points.txt
modsys-0.5.1.dist-info/top_level.txt
modsys-0.5.1.dist-info/RECORD
