Metadata-Version: 2.1
Name: modsys
Version: 0.5.1
Summary: A radically simple framework for ML/AI model management
Home-page: https://github.com/modsysML/modsys
Author: ModsysML
Author-email: adrbrownx@gmail.com
License: Apache License, Version 2.0
Platform: Any
Classifier: Operating System :: OS Independent
Classifier: Programming Language :: Python :: 3
License-File: LICENSE
Requires-Dist: Django (>3.0)
Requires-Dist: firebase-admin (==6.2.0)
Requires-Dist: google-api-core (==2.11.1)
Requires-Dist: google-api-python-client (==2.92.0)
Requires-Dist: google-auth (==2.21.0)
Requires-Dist: google-auth-httplib2 (==0.1.0)
Requires-Dist: google-cloud-core (==2.3.3)
Requires-Dist: google-cloud-firestore (==2.11.1)
Requires-Dist: google-cloud-storage (==2.10.0)
Requires-Dist: google-crc32c (==1.5.0)
Requires-Dist: google-resumable-media (==2.5.0)
Requires-Dist: googleapis-common-protos (==1.59.1)
Requires-Dist: Jinja2 (==3.1.2)
Requires-Dist: openai (==0.27.7)
Requires-Dist: psycopg (==3.1.6)
Requires-Dist: psycopg-binary (==3.1.6)
Requires-Dist: psycopg-pool (==3.1.7)
Requires-Dist: psycopg2-binary (==2.9.6)
Requires-Dist: python-dotenv (==1.0.0)
Requires-Dist: requests (==2.28.1)
Requires-Dist: tabulate (==0.9.0)
Requires-Dist: termcolor (==2.3.0)
Requires-Dist: tqdm (==4.65.0)
Requires-Dist: virtualenv (==20.21.0)
